<?xml version="1.0" encoding="UTF-8"?>
<objects serializationModel="Studio.02.02.00">
	<object class="AudioFile" id="{752b9844-7c7d-4fb0-a085-f328e6284df2}">
		<property name="assetPath">
			<value>OS_FA2_Wood_Hit_4.wav</value>
		</property>
		<property name="frequencyInKHz">
			<value>44.0999985</value>
		</property>
		<property name="channelCount">
			<value>2</value>
		</property>
		<property name="length">
			<value>0.94591836734693879</value>
		</property>
		<relationship name="masterAssetFolder">
			<destination>{f66b6c2d-4252-4ec0-8944-ed549e18c1e0}</destination>
		</relationship>
	</object>
</objects>
